mmray/HRE.py
mmray/TRE.py
mmray/__init__.py
mmray/base.py
mmray/generate_slurm_script.py
mmray-0.1.2.dist-info/METADATA
mmray-0.1.2.dist-info/WHEEL
mmray-0.1.2.dist-info/entry_points.txt
mmray-0.1.2.dist-info/licenses/LICENSE
mmray-0.1.2.dist-info/RECORD
