Metadata-Version: 2.4
Name: mmray
Version: 0.1.2
Summary: Add your description here
License-File: LICENSE
Requires-Python: >=3.12
Requires-Dist: ray[default]>=2.38.0
